{
  "$comment": "Hand-derivation (merge.md §5/§6/§8). This vector's inputs/expect are STRUCTURALLY identical to .kontourai/flow-agents/hachure-identifier-merge/design.md §11 'Worked example + independent hand-derivation' -- the bundle-level source/producerId values were genericized from design.md §11's worked example (survey -> producer-a, veritas -> producer-b, flow -> producer-c; mapping recorded in this session's deliver.md History) to keep this shipped, machine-checked conformance fixture vendor-neutral, consistent with the rest of this repo's conformance vectors and merge.md's own examples (plan.md AC7). This rename does NOT change expect: source/producerId are bundle-level fields, not part of the Claim record being compared, so the tie-break outcome below is unaffected -- re-derived by hand against the renamed inputs. shared.claim.x appears in Bundle A (subjectId r1, surface readiness, claimType coverage, value 91) and Bundle B (subjectId r2, surface governance, claimType policy-check, value true) -- content differs under the same id, so per merge.md §5 rule 2 this is a collision, reported as {collection: 'claims', id: 'shared.claim.x'}. Per merge.md §6's tie-break, compute a canonical (sorted-key) serialization of each variant: A's serialization starts '{\\\"claimType\\\":\\\"coverage\\\",...}', B's starts '{\\\"claimType\\\":\\\"policy-check\\\",...}' -- lexicographically 'coverage' < 'policy-check' ('c' < 'p'), so A's record is the deterministically-kept content regardless of whether the implementation is handed [A,B,C], [B,A,C], [C,B,A], or any other permutation of the 3 inputs -- this is the vector that exercises the order-independence MUST (test/merge.test.mjs asserts identical output across every permutation of inputs). Bundle C's claim ('unrelated.claim.y') never collides with anything, and its id is a distinct string never repeated. Status-function.md Step 6 ('no policy, no evidence') applies to both surviving claim ids ('shared.claim.x' from kept content A, and 'unrelated.claim.y') since no bundle attaches any policy or evidence/events -> both derive 'unknown'.",
  "now": "2026-06-10T00:00:00.000Z",
  "inputs": [
    {
      "schemaVersion": 4,
      "source": "producer-a",
      "producerId": "producer-a",
      "claims": [
        {
          "id": "shared.claim.x",
          "subjectType": "repo",
          "subjectId": "r1",
          "surface": "readiness",
          "claimType": "coverage",
          "fieldOrBehavior": "coverage",
          "value": 91,
          "createdAt": "2026-06-01T00:00:00.000Z",
          "updatedAt": "2026-06-01T00:00:00.000Z"
        }
      ],
      "evidence": [],
      "policies": [],
      "events": []
    },
    {
      "schemaVersion": 4,
      "source": "producer-b",
      "producerId": "producer-b",
      "claims": [
        {
          "id": "shared.claim.x",
          "subjectType": "repo",
          "subjectId": "r2",
          "surface": "governance",
          "claimType": "policy-check",
          "fieldOrBehavior": "signed-off",
          "value": true,
          "createdAt": "2026-06-01T00:00:00.000Z",
          "updatedAt": "2026-06-01T00:00:00.000Z"
        }
      ],
      "evidence": [],
      "policies": [],
      "events": []
    },
    {
      "schemaVersion": 4,
      "source": "producer-c",
      "producerId": "producer-c",
      "claims": [
        {
          "id": "unrelated.claim.y",
          "subjectType": "gate",
          "subjectId": "g1",
          "surface": "gates",
          "claimType": "gate-status",
          "fieldOrBehavior": "passed",
          "value": true,
          "createdAt": "2026-06-01T00:00:00.000Z",
          "updatedAt": "2026-06-01T00:00:00.000Z"
        }
      ],
      "evidence": [],
      "policies": [],
      "events": []
    }
  ],
  "expect": {
    "mergedClaimIds": [
      "shared.claim.x",
      "unrelated.claim.y"
    ],
    "collisions": [
      {
        "collection": "claims",
        "id": "shared.claim.x"
      }
    ],
    "statusByClaimId": {
      "shared.claim.x": "unknown",
      "unrelated.claim.y": "unknown"
    }
  }
}
